brutemind/__init__.py
brutemind/brutemind.py
brutemind/datasets.py
brutemind/models.py
brutemind-0.29.dev0.dist-info/DESCRIPTION.rst
brutemind-0.29.dev0.dist-info/LICENSE.txt
brutemind-0.29.dev0.dist-info/METADATA
brutemind-0.29.dev0.dist-info/RECORD
brutemind-0.29.dev0.dist-info/WHEEL
brutemind-0.29.dev0.dist-info/metadata.json
brutemind-0.29.dev0.dist-info/top_level.txt
