Metadata-Version: 2.0
Name: brutemind
Version: 0.29.dev0
Summary: UNKNOWN
Home-page: https://gitlab.com/mikecto911/brutemind
Author: Valeriy Garnaga
Author-email: val@cto911.com
License: MIT
Platform: UNKNOWN
Classifier: Development Status :: 3 - Alpha
Classifier: Intended Audience :: Developers
Classifier: Topic :: Software Development :: Build Tools
Classifier: License :: OSI Approved :: MIT License
Classifier: Operating System :: OS Independent
Classifier: Programming Language :: Python :: 3.4
Classifier: Programming Language :: Python :: 3.5
Classifier: Programming Language :: Python :: 3.6
